pynxm.py
pynxm-0.1.0.dist-info/LICENSE
pynxm-0.1.0.dist-info/WHEEL
pynxm-0.1.0.dist-info/METADATA
pynxm-0.1.0.dist-info/RECORD
