Metadata-Version: 2.1
Name: pynxm
Version: 0.1.0
Summary: A python wrapper for the Nexus API.
Home-page: https://github.com/GandaG/pynexus
License: UNKNOWN
Author: Daniel Nunes
Author-email: daniel.henri.nunes@gmail.com
Classifier: Intended Audience :: Developers
Classifier: License :: OSI Approved :: Apache Software License
Classifier: Programming Language :: Python :: 2
Classifier: Programming Language :: Python :: 3
Classifier: Topic :: Software Development :: Libraries
Requires-Dist: requests
Requires-Dist: websocket-client
Requires-Dist: tox; extra == "dev"
Requires-Dist: bump2version; extra == "dev"
Provides-Extra: dev
